sdp_test_package/__init__.py
sdp_test_package/main.py
sdp_test_package/mod1.py
sdp_test_package-0.1.dist-info/DESCRIPTION.rst
sdp_test_package-0.1.dist-info/METADATA
sdp_test_package-0.1.dist-info/RECORD
sdp_test_package-0.1.dist-info/WHEEL
sdp_test_package-0.1.dist-info/metadata.json
sdp_test_package-0.1.dist-info/top_level.txt
